vec/__init__.py
vec-0.7.1.dist-info/LICENSE
vec-0.7.1.dist-info/WHEEL
vec-0.7.1.dist-info/METADATA
vec-0.7.1.dist-info/RECORD
