Metadata-Version: 2.1
Name: vec
Version: 0.7.1
Summary: A 2-dimensional vector class designed to be convenient
Home-page: https://github.com/larryhastings/vec/
Author: Larry Hastings
Author-email: larry@hastings.org
Requires-Python: >=3.6
Classifier: Intended Audience :: Developers
Classifier: License :: OSI Approved :: BSD License
Classifier: Programming Language :: Python :: 3 :: Only
